octoprint_firmware_check/__init__.py
octoprint_firmware_check/checks/__init__.py
octoprint_firmware_check/checks/firmware_broken.py
octoprint_firmware_check/checks/firmware_development.py
octoprint_firmware_check/checks/firmware_hostcommands.py
octoprint_firmware_check/checks/firmware_unsafe.py
octoprint_firmware_check/static/clientjs/firmware_check.js
octoprint_firmware_check/static/css/firmware_check.css
octoprint_firmware_check/static/js/firmware_check.js
octoprint_firmware_check/static/less/firmware_check.less
octoprint_firmware_check/templates/firmware_check_settings.jinja2
octoprint_firmware_check/templates/firmware_check_sidebar_info.jinja2
octoprint_firmware_check/templates/firmware_check_sidebar_warning.jinja2
octoprint_firmware_check/translations/de/LC_MESSAGES/messages.mo
octoprint_firmware_check/translations/de/LC_MESSAGES/messages.po
OctoPrint_FirmwareCheck-2025.5.14.dist-info/LICENSE
OctoPrint_FirmwareCheck-2025.5.14.dist-info/METADATA
OctoPrint_FirmwareCheck-2025.5.14.dist-info/WHEEL
OctoPrint_FirmwareCheck-2025.5.14.dist-info/entry_points.txt
OctoPrint_FirmwareCheck-2025.5.14.dist-info/top_level.txt
OctoPrint_FirmwareCheck-2025.5.14.dist-info/RECORD
