Metadata-Version: 2.1
Name: OctoPrint-FirmwareCheck
Version: 2025.5.14
Summary: Checks for unsafe or broken printer firmwares
Home-page: https://github.com/OctoPrint/OctoPrint-FirmwareCheck
Author: Gina Häußge
Author-email: gina@octoprint.org
License: AGPLv3
License-File: LICENSE
Provides-Extra: develop
Requires-Dist: pre-commit; extra == "develop"
